[
  {
    "title": "Minimalist Living Room Inspiration",
    "image": "/decor/minimalist-living-room.jpg",
    "url": "https://www.ikea.com/us/en/rooms/living-room/",
    "suggestion": "Try neutral tones and multi-purpose furniture for a calm, clutter-free space."
  },
  {
    "title": "Eco-Friendly Bedroom Decor",
    "image": "/decor/eco-bedroom.jpg",
    "url": "https://www.westelm.com/shop/new/eco-friendly/",
    "suggestion": "Use organic bedding and plants to purify air and add a fresh look."
  },
  {
    "title": "Functional Entryway Ideas",
    "image": "/decor/entryway.jpg",
    "url": "https://www.containerstore.com/entryway",
    "suggestion": "Add wall hooks and a shoe bench to keep entrances tidy."
  }
]
